qualesim_quantumsim/__init__.py
qualesim_quantumsim/__main__.py
qualesim_quantumsim/backend.py
qualesim_quantumsim/qubit.py
qualesim_quantumsim-1.0.3.data/data/bin/dqcsbequantumsim
qualesim_quantumsim-1.0.3.dist-info/LICENSE
qualesim_quantumsim-1.0.3.dist-info/METADATA
qualesim_quantumsim-1.0.3.dist-info/WHEEL
qualesim_quantumsim-1.0.3.dist-info/top_level.txt
qualesim_quantumsim-1.0.3.dist-info/RECORD
